Workbook
Name age: #REF!
Name count: #REF!
Name worth: #REF!

Sheet Dashboard
B14: Task ID | C14: Task Name | D14: Team | E14: Task Owner | F14: Start Date | G14: Due Date | H14: Task Duration | I14: Status | J14: Overdue? | K14: Comments
B15: T001 | C15: Prepare Q4 Financial Report | D15: Finance | E15: Sarah Johnson | F15: 46267 | G15: 46285 | H15: =Table1[[#This Row],[Due Date]]-Table1[[#This Row],[Start Date]] -> 18 | I15: Completed | J15: =AND(Table1[[#This Row],[Status]]<>"Completed",Table1[[#This Row],[Due Date]]<TODAY()) -> FALSE | K15: Submitted to CFO for review.
B16: T002 | C16: Conduct Market Research | D16: Strategy | E16: Sarah Johnson | F16: 46270 | G16: 46290 | H16: =Table1[[#This Row],[Due Date]]-Table1[[#This Row],[Start Date]] -> 20 | I16: Completed | J16: =AND(Table1[[#This Row],[Status]]<>"Completed",Table1[[#This Row],[Due Date]]<TODAY()) -> FALSE | K16: Draft findings ready; awaiting survey data.
B17: T003 | C17: Redesign Website Homepage | D17: Strategy | E17: David Kim | F17: 46213 | G17: 46239 | H17: =Table1[[#This Row],[Due Date]]-Table1[[#This Row],[Start Date]] -> 26 | I17: In Progress | J17: =AND(Table1[[#This Row],[Status]]<>"Completed",Table1[[#This Row],[Due Date]]<TODAY()) -> TRUE | K17: Wireframes approved; development in progress.
B18: T004 | C18: Update Sales Forecast for FY2026 | D18: Finance | E18: Sarah Johnson | F18: 46277 | G18: 46295 | H18: =Table1[[#This Row],[Due Date]]-Table1[[#This Row],[Start Date]] -> 18 | I18: Completed | J18: =AND(Table1[[#This Row],[Status]]<>"Completed",Table1[[#This Row],[Due Date]]<TODAY()) -> FALSE | K18: Final version shared with Sales Director.
B19: T005 | C19: Implement CRM Upgrade | D19: Strategy | E19: James Miller | F19: 46280 | G19: 46305 | H19: =Table1[[#This Row],[Due Date]]-Table1[[#This Row],[Start Date]] -> 25 | I19: In Progress | J19: =AND(Table1[[#This Row],[Status]]<>"Completed",Table1[[#This Row],[Due Date]]<TODAY()) -> FALSE | K19: Vendor confirmed delivery timeline.
B20: T006 | C20: Plan Annual Company Retreat | D20: HR | E20: David Kim | F20: 46283 | G20: 46310 | H20: =Table1[[#This Row],[Due Date]]-Table1[[#This Row],[Start Date]] -> 27 | I20: In Progress | J20: =AND(Table1[[#This Row],[Status]]<>"Completed",Table1[[#This Row],[Due Date]]<TODAY()) -> FALSE | K20: Venue options being shortlisted.
B21: T007 | C21: Review Legal for Contracts | D21: HR | E21: Alex Chen | F21: 46254 | G21: 46261 | H21: =Table1[[#This Row],[Due Date]]-Table1[[#This Row],[Start Date]] -> 7 | I21: Not Started | J21: =AND(Table1[[#This Row],[Status]]<>"Completed",Table1[[#This Row],[Due Date]]<TODAY()) -> TRUE | K21: Updated contracts aligned with new regulation.
B22: T008 | C22: Launch Social Media Campaign | D22: Marketing | E22: Alex Chen | F22: 46287 | G22: 46307 | H22: =Table1[[#This Row],[Due Date]]-Table1[[#This Row],[Start Date]] -> 20 | I22: In Progress | J22: =AND(Table1[[#This Row],[Status]]<>"Completed",Table1[[#This Row],[Due Date]]<TODAY()) -> FALSE | K22: Initial creatives approved, campaign scheduled.
B23: T009 | C23: Recruit New Data Analyst | D23: HR | E23: Sarah Johnson | F23: 46288 | G23: 46315 | H23: =Table1[[#This Row],[Due Date]]-Table1[[#This Row],[Start Date]] -> 27 | I23: Completed | J23: =AND(Table1[[#This Row],[Status]]<>"Completed",Table1[[#This Row],[Due Date]]<TODAY()) -> FALSE | K23: First round of interviews completed.
B24: T010 | C24: Conduct Employee Survey | D24: HR | E24: Sarah Johnson | F24: 46289 | G24: 46300 | H24: =Table1[[#This Row],[Due Date]]-Table1[[#This Row],[Start Date]] -> 11 | I24: In Progress | J24: =AND(Table1[[#This Row],[Status]]<>"Completed",Table1[[#This Row],[Due Date]]<TODAY()) -> TRUE | K24: Survey questions finalized.
B25: T011 | C25: Prepare Investor Presentation | D25: Finance | E25: David Kim | F25: 46290 | G25: 46297 | H25: =Table1[[#This Row],[Due Date]]-Table1[[#This Row],[Start Date]] -> 7 | I25: Completed | J25: =AND(Table1[[#This Row],[Status]]<>"Completed",Table1[[#This Row],[Due Date]]<TODAY()) -> FALSE | K25: Draft slides ready; awaiting financial highlights.
B26: T012 | C26: Upgrade Infrastructure | D26: Strategy | E26: Sarah Johnson | F26: 46291 | G26: 46325 | H26: =Table1[[#This Row],[Due Date]]-Table1[[#This Row],[Start Date]] -> 34 | I26: Completed | J26: =AND(Table1[[#This Row],[Status]]<>"Completed",Table1[[#This Row],[Due Date]]<TODAY()) -> FALSE | K26: External consultant engagement pending.
... B119: T105 | C119: Audit Internal Expense Reports | D119: Finance | E119: Emily Davis | F119: 46294 | G119: 46299 | H119: =Table1[[#This Row],[Due Date]]-Table1[[#This Row],[Start Date]] -> 5 | I119: Not Started | J119: =AND(Table1[[#This Row],[Status]]<>"Completed",Table1[[#This Row],[Due Date]]<TODAY()) -> TRUE | K119: Waiting for submission of all departmental reports.

Sheet Support Sheet
B2: Status | C2: Count | E2: Owners | F2: Count | H2: Team | I2: Count | K2: Overdue
B3: Completed | C3: =COUNTIF(Table1[Status],'Support Sheet'!B3) -> 42 | E3: Sarah Johnson | F3: =COUNTIF(Table1[Task Owner], 'Support Sheet'!E3) -> 25 | H3: Finance | I3: =COUNTIF(Table1[Team],'Support Sheet'!H3) -> 27 | K3: =COUNTIF(Table1[Overdue?], TRUE) -> 13
B4: In Progress | C4: =COUNTIF(Table1[Status],'Support Sheet'!B4) -> 40 | E4: David Kim | F4: =COUNTIF(Table1[Task Owner], 'Support Sheet'!E4) -> 21 | H4: Strategy | I4: =COUNTIF(Table1[Team],'Support Sheet'!H4) -> 32
B5: Not Started | C5: =COUNTIF(Table1[Status],'Support Sheet'!B5) -> 23 | E5: James Miller | F5: =COUNTIF(Table1[Task Owner], 'Support Sheet'!E5) -> 18 | H5: HR | I5: =COUNTIF(Table1[Team],'Support Sheet'!H5) -> 25
B6: Total | C6: =SUM(C3:C5) -> 105 | E6: Alex Chen | F6: =COUNTIF(Table1[Task Owner], 'Support Sheet'!E6) -> 20 | H6: Marketing | I6: =COUNTIF(Table1[Team],'Support Sheet'!H6) -> 21
E7: Emily Davis | F7: =COUNTIF(Table1[Task Owner], 'Support Sheet'!E7) -> 21
